reddit_scraper/__init__.py
reddit_scraper/reddit_scraper.py
reddit_scraper_tool-0.1.0.dist-info/licenses/LICENSE
reddit_scraper_tool-0.1.0.dist-info/METADATA
reddit_scraper_tool-0.1.0.dist-info/WHEEL
reddit_scraper_tool-0.1.0.dist-info/top_level.txt
reddit_scraper_tool-0.1.0.dist-info/RECORD
