Metadata-Version: 2.4
Name: reddit-scraper-tool
Version: 0.1.0
Summary: A Python package for scraping Reddit user data.
Home-page: https://github.com/ininike/reddit-scraper
Author: Inioluwa Adenaike
Author-email: inioluwadenaike@gmail.com
Classifier: Programming Language :: Python :: 3
Classifier: License :: OSI Approved :: MIT License
Classifier: Operating System :: OS Independent
Requires-Python: >=3.6
License-File: LICENSE
Requires-Dist: aiohttp
Dynamic: author
Dynamic: author-email
Dynamic: classifier
Dynamic: description
Dynamic: description-content-type
Dynamic: home-page
Dynamic: license-file
Dynamic: requires-dist
Dynamic: requires-python
Dynamic: summary
